sphinx_accessibility/__init__.py
sphinx_accessibility/_version.py
sphinx_accessibility/assets/html/Accessibility.js
sphinx_accessibility/assets/html/HighContrast.css
sphinx_accessibility/assets/html/OpenDyslexic-Bold-Italic.woff
sphinx_accessibility/assets/html/OpenDyslexic-Bold-Italic.woff2
sphinx_accessibility/assets/html/OpenDyslexic-Bold.woff
sphinx_accessibility/assets/html/OpenDyslexic-Bold.woff2
sphinx_accessibility/assets/html/OpenDyslexic-Italic.woff
sphinx_accessibility/assets/html/OpenDyslexic-Italic.woff2
sphinx_accessibility/assets/html/OpenDyslexic-Regular.woff
sphinx_accessibility/assets/html/OpenDyslexic-Regular.woff2
sphinx_accessibility/assets/html/OpenDyslexic.css
sphinx_accessibility/assets/html/SVGstyling.css
sphinx_accessibility/translations/README.md
sphinx_accessibility/translations/_convert.py
sphinx_accessibility/translations/jsons/DisableContrast.json
sphinx_accessibility/translations/jsons/DisableFont.json
sphinx_accessibility/translations/jsons/EnableContrast.json
sphinx_accessibility/translations/jsons/EnableFont.json
sphinx_accessibility/translations/locales/ar/LC_MESSAGES/accessibility.mo
sphinx_accessibility/translations/locales/ar/LC_MESSAGES/accessibility.po
sphinx_accessibility/translations/locales/bn/LC_MESSAGES/accessibility.mo
sphinx_accessibility/translations/locales/bn/LC_MESSAGES/accessibility.po
sphinx_accessibility/translations/locales/cs/LC_MESSAGES/accessibility.mo
sphinx_accessibility/translations/locales/cs/LC_MESSAGES/accessibility.po
sphinx_accessibility/translations/locales/de/LC_MESSAGES/accessibility.mo
sphinx_accessibility/translations/locales/de/LC_MESSAGES/accessibility.po
sphinx_accessibility/translations/locales/el/LC_MESSAGES/accessibility.mo
sphinx_accessibility/translations/locales/el/LC_MESSAGES/accessibility.po
sphinx_accessibility/translations/locales/es/LC_MESSAGES/accessibility.mo
sphinx_accessibility/translations/locales/es/LC_MESSAGES/accessibility.po
sphinx_accessibility-1.0.1.dist-info/METADATA
sphinx_accessibility-1.0.1.dist-info/WHEEL
sphinx_accessibility-1.0.1.dist-info/licenses/LICENSE
sphinx_accessibility-1.0.1.dist-info/RECORD
