Metadata-Version: 2.4
Name: sphinx-accessibility
Version: 1.0.1
Summary: Sphinx extension that provides accessibility features.
Author-email: Dennis den Ouden-van der Horst <d.denouden-vanderhorst@tudelft.nl>
License: MIT License
License-File: LICENSE
Requires-Python: >=3.10
Requires-Dist: sphinx
